CHANGES.txt
LICENSE.txt
MANIFEST.in
README.rst
setup.cfg
setup.py
SkewTplus/__init__.py
SkewTplus/_thermodynamics.cpp
SkewTplus/_thermodynamics.pyx
SkewTplus/common.pxd
SkewTplus/errorHandling.py
SkewTplus/skewT.py
SkewTplus/sounding.py
SkewTplus/thermodynamics.py
SkewTplus.egg-info/PKG-INFO
SkewTplus.egg-info/SOURCES.txt
SkewTplus.egg-info/dependency_links.txt
SkewTplus.egg-info/requires.txt
SkewTplus.egg-info/top_level.txt
examples/94610.2010032200.txt
examples/94866.2010030600.txt
examples/94975.2013070200.txt
examples/94975.2013070900.txt
examples/armSoundingExample.cdf
examples/armSoundingPlot.py
examples/bna_day1.txt
examples/bna_day2.txt
examples/exampleSounding.txt
examples/parcelAnalysisExample.py
examples/soundingFromWeb.py
examples/soundingPlot.py
examples/soundingPlot2.py
examples/soundingQuickView.py
examples/sounding_high_tropo.txt
examples/tests.py
examples/twoSoundingPlots.py
examples/wrfOutputCAPE.py
examples/wrfOutputExample.nc
examples/wrfOutputSunding.py
examples/wrfOutputSunding2.py