Metadata-Version: 1.1
Name: SkewTplus
Version: 1.1.2
Summary: Atmospheric Profile Plotting and Diagnostics
Home-page: http://pypi.python.org/pypi/SkewTplus/
Author: Andres Perez Hortal
Author-email: andresperezcba@gmail.com
License: LICENSE.txt
Platform: UNKNOWN
Classifier: Development Status :: 5 - Production/Stable
Classifier: Intended Audience :: Science/Research
Classifier: Topic :: Scientific/Engineering
Classifier: Topic :: Scientific/Engineering :: Atmospheric Science
Classifier: License :: OSI Approved :: BSD License
Classifier: Programming Language :: Python :: 2
Classifier: Programming Language :: Python :: 2.7
Classifier: Programming Language :: Python :: 3
Classifier: Programming Language :: Python :: 3.6
Classifier: Programming Language :: Cython
